setup.py
reflex/__init__.py
reflex/api.py
reflex/clients.py
reflex/exceptions.py
reflex/mixins.py
reflex_client.egg-info/PKG-INFO
reflex_client.egg-info/SOURCES.txt
reflex_client.egg-info/dependency_links.txt
reflex_client.egg-info/top_level.txt