Metadata-Version: 1.1
Name: reflex-client
Version: 0.0.2
Summary: Reflex Python client
Home-page: https://github.com/immunda/reflex-py
Author: Phil Howell
Author-email: phil@quae.co.uk
License: UNKNOWN
Platform: UNKNOWN
Classifier: Development Status :: 1 - Planning
Classifier: Programming Language :: Python
Classifier: Programming Language :: Python :: 2
Classifier: Programming Language :: Python :: 2.6
Classifier: Programming Language :: Python :: 2.7
